<Info>
  <Pages>
    <Page Number="1" Width="1381" Height="1843">
      <Images>
        <Normal Path="images/page1.swf" FileSize="90" />
        <Thumbnail Path="images/page1_thumbnail.jpg" FileSize="22" />
        <Zoomed Path="images/page1.swf" FileSize="90" />
      </Images>
      <Buttons />
    </Page>
    <Page Number="2" Width="1381" Height="1843">
      <Images>
        <Normal Path="images/page2.swf" FileSize="349" />
        <Thumbnail Path="images/page2_thumbnail.jpg" FileSize="34" />
        <Zoomed Path="images/page2.swf" FileSize="349" />
      </Images>
      <Buttons />
    </Page>
    <Page Number="3" Width="1381" Height="1843">
      <Images>
        <Normal Path="images/page3.swf" FileSize="161" />
        <Thumbnail Path="images/page3_thumbnail.jpg" FileSize="21" />
        <Zoomed Path="images/page3.swf" FileSize="161" />
      </Images>
      <Buttons />
    </Page>
    <Page Number="4" Width="1381" Height="1843">
      <Images>
        <Normal Path="images/page4.swf" FileSize="282" />
        <Thumbnail Path="images/page4_thumbnail.jpg" FileSize="18" />
        <Zoomed Path="images/page4.swf" FileSize="282" />
      </Images>
      <Buttons />
    </Page>
    <Page Number="5" Width="1381" Height="1843">
      <Images>
        <Normal Path="images/page5.swf" FileSize="447" />
        <Thumbnail Path="images/page5_thumbnail.jpg" FileSize="33" />
        <Zoomed Path="images/page5.swf" FileSize="447" />
      </Images>
      <Buttons />
    </Page>
    <Page Number="6" Width="1381" Height="1843">
      <Images>
        <Normal Path="images/page6.swf" FileSize="642" />
        <Thumbnail Path="images/page6_thumbnail.jpg" FileSize="30" />
        <Zoomed Path="images/page6.swf" FileSize="642" />
      </Images>
      <Buttons />
    </Page>
    <Page Number="7" Width="1381" Height="1843">
      <Images>
        <Normal Path="images/page7.swf" FileSize="258" />
        <Thumbnail Path="images/page7_thumbnail.jpg" FileSize="29" />
        <Zoomed Path="images/page7.swf" FileSize="258" />
      </Images>
      <Buttons />
    </Page>
    <Page Number="8" Width="1381" Height="1843">
      <Images>
        <Normal Path="images/page8.swf" FileSize="430" />
        <Thumbnail Path="images/page8_thumbnail.jpg" FileSize="22" />
        <Zoomed Path="images/page8.swf" FileSize="430" />
      </Images>
      <Buttons />
    </Page>
    <Page Number="9" Width="1381" Height="1843">
      <Images>
        <Normal Path="images/page9.swf" FileSize="352" />
        <Thumbnail Path="images/page9_thumbnail.jpg" FileSize="22" />
        <Zoomed Path="images/page9.swf" FileSize="352" />
      </Images>
      <Buttons />
    </Page>
    <Page Number="10" Width="1381" Height="1843">
      <Images>
        <Normal Path="images/page10.swf" FileSize="257" />
        <Thumbnail Path="images/page10_thumbnail.jpg" FileSize="36" />
        <Zoomed Path="images/page10.swf" FileSize="257" />
      </Images>
      <Buttons />
    </Page>
    <Page Number="11" Width="1381" Height="1843">
      <Images>
        <Normal Path="images/page11.swf" FileSize="422" />
        <Thumbnail Path="images/page11_thumbnail.jpg" FileSize="35" />
        <Zoomed Path="images/page11.swf" FileSize="422" />
      </Images>
      <Buttons />
    </Page>
    <Page Number="12" Width="1381" Height="1843">
      <Images>
        <Normal Path="images/page12.swf" FileSize="635" />
        <Thumbnail Path="images/page12_thumbnail.jpg" FileSize="36" />
        <Zoomed Path="images/page12.swf" FileSize="635" />
      </Images>
      <Buttons />
    </Page>
    <Page Number="13" Width="1381" Height="1843">
      <Images>
        <Normal Path="images/page13.swf" FileSize="534" />
        <Thumbnail Path="images/page13_thumbnail.jpg" FileSize="26" />
        <Zoomed Path="images/page13.swf" FileSize="534" />
      </Images>
      <Buttons />
    </Page>
    <Page Number="14" Width="1381" Height="1843">
      <Images>
        <Normal Path="images/page14.swf" FileSize="407" />
        <Thumbnail Path="images/page14_thumbnail.jpg" FileSize="34" />
        <Zoomed Path="images/page14.swf" FileSize="407" />
      </Images>
      <Buttons />
    </Page>
    <Page Number="15" Width="1381" Height="1843">
      <Images>
        <Normal Path="images/page15.swf" FileSize="163" />
        <Thumbnail Path="images/page15_thumbnail.jpg" FileSize="22" />
        <Zoomed Path="images/page15.swf" FileSize="163" />
      </Images>
      <Buttons />
    </Page>
    <Page Number="16" Width="1381" Height="1843">
      <Images>
        <Normal Path="images/page16.swf" FileSize="240" />
        <Thumbnail Path="images/page16_thumbnail.jpg" FileSize="26" />
        <Zoomed Path="images/page16.swf" FileSize="240" />
      </Images>
      <Buttons />
    </Page>
    <Page Number="17" Width="1381" Height="1843">
      <Images>
        <Normal Path="images/page17.swf" FileSize="211" />
        <Thumbnail Path="images/page17_thumbnail.jpg" FileSize="25" />
        <Zoomed Path="images/page17.swf" FileSize="211" />
      </Images>
      <Buttons />
    </Page>
    <Page Number="18" Width="1381" Height="1843">
      <Images>
        <Normal Path="images/page18.swf" FileSize="173" />
        <Thumbnail Path="images/page18_thumbnail.jpg" FileSize="21" />
        <Zoomed Path="images/page18.swf" FileSize="173" />
      </Images>
      <Buttons />
    </Page>
    <Page Number="19" Width="1381" Height="1843">
      <Images>
        <Normal Path="images/page19.swf" FileSize="274" />
        <Thumbnail Path="images/page19_thumbnail.jpg" FileSize="29" />
        <Zoomed Path="images/page19.swf" FileSize="274" />
      </Images>
      <Buttons />
    </Page>
    <Page Number="20" Width="1381" Height="1843">
      <Images>
        <Normal Path="images/page20.swf" FileSize="127" />
        <Thumbnail Path="images/page20_thumbnail.jpg" FileSize="29" />
        <Zoomed Path="images/page20.swf" FileSize="127" />
      </Images>
      <Buttons />
    </Page>
  </Pages>
  <TableOfContents />
</Info>